greedy/__init__.py
greedy/greedy.py
tests/__init__.py
tests/test_greedy.py
greedy-0.1.1.dist-info/LICENSE
greedy-0.1.1.dist-info/METADATA
greedy-0.1.1.dist-info/WHEEL
greedy-0.1.1.dist-info/top_level.txt
greedy-0.1.1.dist-info/RECORD
