Metadata-Version: 2.1
Name: greedy
Version: 0.1.1
Summary: Greedy (topological) coloring for GeoPandas
Home-page: https://github.com/martinfleis/greedy
Author: Martin Fleischmann
Author-email: martin@martinfleischmann.net
License: UNKNOWN
Platform: UNKNOWN
Classifier: Programming Language :: Python :: 3
Classifier: License :: OSI Approved :: GNU General Public License v3 (GPLv3)
Classifier: Operating System :: OS Independent
Requires-Python: >=3.6
Requires-Dist: geopandas
Requires-Dist: networkx
Requires-Dist: libpysal
